pjdate/core.py
pjdate/init.py
pjdate-0.0.1.dist-info/licenses/LICENSE
pjdate-0.0.1.dist-info/METADATA
pjdate-0.0.1.dist-info/WHEEL
pjdate-0.0.1.dist-info/top_level.txt
pjdate-0.0.1.dist-info/RECORD
