Metadata-Version: 2.4
Name: pjdate
Version: 0.0.1
Summary: A small package for java date formater
Author-email: Neil <piecivalnie@gmail.com>
License-Expression: MIT
Project-URL: Homepage, https://github.com/cgnie/pjdate
Project-URL: Issues, https://github.com/cgnie/pjdate
Classifier: Programming Language :: Python :: 3
Classifier: Operating System :: OS Independent
License-File: LICENSE
Dynamic: license-file
